aigis/__init__.py
aigis/skeleton.py
aigis-0.0.0.dist-info/LICENSE.txt
aigis-0.0.0.dist-info/METADATA
aigis-0.0.0.dist-info/WHEEL
aigis-0.0.0.dist-info/top_level.txt
aigis-0.0.0.dist-info/RECORD
