Metadata-Version: 2.2
Name: aigis
Version: 0.0.0
Summary: Add a short description here!
Home-page: https://aigis.org/
Author: Zhe Tao
Author-email: zhetao@ucdavis.edu
License: Proprietary
Project-URL: Documentation, https://pyscaffold.org/
Platform: any
Classifier: Development Status :: 4 - Beta
Classifier: Programming Language :: Python
License-File: LICENSE.txt
Requires-Dist: importlib-metadata; python_version < "3.8"
Provides-Extra: testing
Requires-Dist: setuptools; extra == "testing"
Requires-Dist: pytest; extra == "testing"
Requires-Dist: pytest-cov; extra == "testing"
